dataguild/__init__.py
dataguild/cli.py
dataguild/ai/__init__.py
dataguild/ai/gemma_client.py
dataguild/ai/intelligent_extractor.py
dataguild/ai/metadata_intelligence_engine.py
dataguild/api/__init__.py
dataguild/api/closeable.py
dataguild/api/common.py
dataguild/api/decorators.py
dataguild/api/incremental_lineage_helper.py
dataguild/api/incremental_properties_helper.py
dataguild/api/report.py
dataguild/api/source.py
dataguild/api/source_helpers.py
dataguild/api/workunit.py
dataguild/competitive/__init__.py
dataguild/competitive/feature_matrix.py
dataguild/configuration/__init__.py
dataguild/configuration/common.py
dataguild/configuration/connection_resolver.py
dataguild/configuration/datetimes.py
dataguild/configuration/pattern_utils.py
dataguild/configuration/source_common.py
dataguild/configuration/time_window_config.py
dataguild/configuration/validate_field_removal.py
dataguild/configuration/validate_field_rename.py
dataguild/connectors/__init__.py
dataguild/connectors/universal_connector_framework.py
dataguild/database/hybrid_client.py
dataguild/database/migration_script.py
dataguild/database/neo4j_client.py
dataguild/database/postgresql_client.py
dataguild/emitter/__init__.py
dataguild/emitter/advanced_emitter.py
dataguild/emitter/cli_integration.py
dataguild/emitter/dataguild_kafka_emitter.py
dataguild/emitter/dataguild_rest_emitter.py
dataguild/emitter/emitter_factory.py
dataguild/emitter/enhanced_mcp_builder.py
dataguild/emitter/examples.py
dataguild/emitter/mce_builder.py
dataguild/emitter/mcp.py
dataguild/emitter/mcp_builder.py
dataguild/emitter/snowflake_integration.py
dataguild/glossary/classification_mixin.py
dataguild/graph/__init__.py
dataguild/graph/client.py
dataguild/metadata/__init__.py
dataguild/metadata/schema_classes.py
dataguild/metadata/schemas.py
dataguild/metadata/urns.py
dataguild/metadata/com/linkedin/pegasus2avro/__init__.py
dataguild/metadata/com/linkedin/pegasus2avro/assertion.py
dataguild/metadata/com/linkedin/pegasus2avro/common.py
dataguild_snowflake_connector-1.1.4.dist-info/licenses/LICENSE
dataguild_snowflake_connector-1.1.4.dist-info/METADATA
dataguild_snowflake_connector-1.1.4.dist-info/WHEEL
dataguild_snowflake_connector-1.1.4.dist-info/entry_points.txt
dataguild_snowflake_connector-1.1.4.dist-info/top_level.txt
dataguild_snowflake_connector-1.1.4.dist-info/RECORD
