Metadata-Version: 2.4
Name: dataguild-snowflake-connector
Version: 1.1.4
Summary: 🚀 Production-Ready Snowflake Metadata Connector with AI-Powered Intelligence
Home-page: https://github.com/dataguild/snowflake-connector
Author: DataGuild Engineering Team
Author-email: engineering@dataguild.com
Project-URL: Bug Tracker, https://github.com/dataguild/snowflake-connector/issues
Project-URL: Documentation, https://dataguild-snowflake.readthedocs.io
Project-URL: Source Code, https://github.com/dataguild/snowflake-connector
Keywords: snowflake,metadata,data-catalog,lineage,dataguild,etl,data-engineering,data-governance,data-quality,ai,machine-learning,data-intelligence,metadata-extraction,data-discovery,enterprise,production-ready
Classifier: Development Status :: 5 - Production/Stable
Classifier: Intended Audience :: Developers
Classifier: Intended Audience :: Information Technology
Classifier: License :: OSI Approved :: Apache Software License
Classifier: Operating System :: OS Independent
Classifier: Programming Language :: Python :: 3
Classifier: Programming Language :: Python :: 3.8
Classifier: Programming Language :: Python :: 3.9
Classifier: Programming Language :: Python :: 3.10
Classifier: Programming Language :: Python :: 3.11
Classifier: Programming Language :: Python :: 3.12
Classifier: Topic :: Database
Classifier: Topic :: Scientific/Engineering :: Information Analysis
Classifier: Topic :: Software Development :: Libraries :: Python Modules
Classifier: Topic :: System :: Archiving :: Backup
Requires-Python: >=3.8
License-File: LICENSE
Requires-Dist: pydantic<2.0.0,>=1.10.0
Requires-Dist: snowflake-connector-python>=3.0.0
Requires-Dist: sqlparse>=0.4.0
Requires-Dist: PyYAML>=6.0
Requires-Dist: click>=8.0.0
Requires-Dist: typing-extensions>=4.0.0
Requires-Dist: sqlalchemy>=1.4.0
Requires-Dist: pandas>=1.3.0
Requires-Dist: structlog>=22.0.0
Requires-Dist: psutil>=5.8.0
Requires-Dist: snowflake-sqlalchemy>=1.4.0
Requires-Dist: prometheus-client>=0.15.0
Requires-Dist: psycopg2-binary>=2.9.0
Requires-Dist: neo4j>=5.0.0
Requires-Dist: sqlglot>=10.0.0
Requires-Dist: networkx>=2.6.0
Requires-Dist: requests>=2.25.0
Requires-Dist: urllib3>=1.26.0
Provides-Extra: dev
Requires-Dist: pytest>=7.0.0; extra == "dev"
Requires-Dist: pytest-cov>=4.0.0; extra == "dev"
Requires-Dist: pytest-mock>=3.6.0; extra == "dev"
Requires-Dist: pytest-asyncio>=0.21.0; extra == "dev"
Requires-Dist: black>=22.0.0; extra == "dev"
Requires-Dist: flake8>=5.0.0; extra == "dev"
Requires-Dist: mypy>=0.991; extra == "dev"
Requires-Dist: isort>=5.10.0; extra == "dev"
Requires-Dist: pre-commit>=2.17.0; extra == "dev"
Requires-Dist: tox>=3.24.0; extra == "dev"
Provides-Extra: docs
Requires-Dist: sphinx>=5.0.0; extra == "docs"
Requires-Dist: sphinx-rtd-theme>=1.0.0; extra == "docs"
Requires-Dist: sphinx-autodoc-typehints>=1.12.0; extra == "docs"
Requires-Dist: myst-parser>=0.18.0; extra == "docs"
Provides-Extra: test
Requires-Dist: pytest>=7.0.0; extra == "test"
Requires-Dist: pytest-cov>=4.0.0; extra == "test"
Requires-Dist: pytest-mock>=3.6.0; extra == "test"
Requires-Dist: pytest-asyncio>=0.21.0; extra == "test"
Requires-Dist: coverage>=6.0.0; extra == "test"
Dynamic: author
Dynamic: author-email
Dynamic: classifier
Dynamic: description
Dynamic: description-content-type
Dynamic: home-page
Dynamic: keywords
Dynamic: license-file
Dynamic: project-url
Dynamic: provides-extra
Dynamic: requires-dist
Dynamic: requires-python
Dynamic: summary
